[
  {
    "firstName": "Fred",
    "lastName": "Allen",
    "sellingProducts": [
      {
        "name": "LANEIGE MYSTIC VEIL FOUNDATION",
        "price": 20.86
      },
      {
        "name": "cough and sore throat",
        "price": 1482.68,
        "buyerFirstName": "Benjamin",
        "buyerLastName": "Henry"
      },
      {
        "name": "XtraCare Foam Antibacterial Hand Wash",
        "price": 1251.97,
        "buyerFirstName": "Ann",
        "buyerLastName": "Stevens"
      },
      {
        "name": "IOPE SUPER VITAL",
        "price": 824.68,
        "buyerLastName": "Moreno"
      },
      {
        "name": "Acetaminophen, Chlorpheniramine Maleate, Dextromethorphan Hydrobromide, Phenylephrine Hydrochloride",
        "price": 1028.27,
        "buyerFirstName": "Patricia",
        "buyerLastName": "Fuller"
      },
      {
        "name": "Finasteride",
        "price": 1374.01,
        "buyerFirstName": "Amanda",
        "buyerLastName": "Frazier"
      },
      {
        "name": "Homeopathic Rheumatism",
        "price": 967.08,
        "buyerFirstName": "Ann",
        "buyerLastName": "Stevens"
      }
    ]
  },
  {
    "lastName": "Baker",
    "sellingProducts": [
      {
        "name": "Echinacea Quartz Gum Support",
        "price": 570.08
      },
      {
        "name": "Effervescent Cold Relief",
        "price": 1436.07,
        "buyerLastName": "Fox"
      }
    ]
  },
  {
    "firstName": "Fred",
    "lastName": "Barnes",
    "sellingProducts": [
      {
        "name": "PANTOPRAZOLE SODIUM",
        "price": 293.89
      },
      {
        "name": "GEMCITABINE",
        "price": 1468.11,
        "buyerFirstName": "Marie",
        "buyerLastName": "Williamson"
      },
      {
        "name": "MEDI-FIRST Non-Aspirin",
        "price": 1301.28,
        "buyerFirstName": "Christina",
        "buyerLastName": "Patterson"
      },
      {
        "name": "No7 Protect and Perfect Foundation Sunscreen Broad Spectrum SPF 15 Cool Ivory",
        "price": 616.19
      },
      {
        "name": "Care One Hemorrhoidal",
        "price": 932.18,
        "buyerLastName": "Bennett"
      },
      {
        "name": "Eszopiclone",
        "price": 405.03
      }
    ]
  },
  {
    "lastName": "Bennett",
    "sellingProducts": [
      {
        "name": "Air",
        "price": 331.53
      },
      {
        "name": "Shopko Lip Treatment",
        "price": 861.42,
        "buyerFirstName": "Benjamin",
        "buyerLastName": "Henry"
      }
    ]
  },
  {
    "firstName": "Anna",
    "lastName": "Clark",
    "sellingProducts": [
      {
        "name": "Childrens Allegra Allergy",
        "price": 650.97
      },
      {
        "name": "Dover Aminophen",
        "price": 192.07
      },
      {
        "name": "Ibuprofen",
        "price": 1305.96,
        "buyerLastName": "Mitchell"
      },
      {
        "name": "SEPHORA Acne-Fighting Mattifying Moisturizer",
        "price": 1019.28,
        "buyerFirstName": "Billy",
        "buyerLastName": "Parker"
      }
    ]
  },
  {
    "firstName": "Patricia",
    "lastName": "Cooper",
    "sellingProducts": [
      {
        "name": "kirkland signature minoxidil",
        "price": 49.17
      },
      {
        "name": "CLARINS Ever Matte SPF 15 - 105 Nude",
        "price": 696.06
      },
      {
        "name": "Ibuprofen",
        "price": 1088.04,
        "buyerFirstName": "Anna",
        "buyerLastName": "Parker"
      }
    ]
  },
  {
    "lastName": "Cunningham",
    "sellingProducts": [
      {
        "name": "Labetalol Hydrochloride",
        "price": 1345.11,
        "buyerFirstName": "Jennifer",
        "buyerLastName": "Riley"
      },
      {
        "name": "Ondansetron",
        "price": 1249.76,
        "buyerFirstName": "Emily",
        "buyerLastName": "Parker"
      },
      {
        "name": "H-Rosacea Formula",
        "price": 99.74
      },
      {
        "name": "leader pain reliever",
        "price": 1179.79,
        "buyerFirstName": "Amanda",
        "buyerLastName": "Frazier"
      },
      {
        "name": "Pollens - Weeds and Garden Plants, Nettle Urtica dioica",
        "price": 782.77,
        "buyerFirstName": "Emily",
        "buyerLastName": "Parker"
      }
    ]
  },
  {
    "firstName": "Sarah",
    "lastName": "Day",
    "sellingProducts": [
      {
        "name": "Cefadroxil",
        "price": 1302.20,
        "buyerFirstName": "Anna",
        "buyerLastName": "Clark"
      },
      {
        "name": "Phenylephrine HCl",
        "price": 459.89
      },
      {
        "name": "up and up temporary minor arthritis pain relief",
        "price": 1085.78,
        "buyerFirstName": "Sandra",
        "buyerLastName": "Riley"
      }
    ]
  },
  {
    "lastName": "Fox",
    "sellingProducts": [
      {
        "name": "SUMATRIPTAN SUCCINATE",
        "price": 1265.94,
        "buyerFirstName": "Arthur",
        "buyerLastName": "Reynolds"
      },
      {
        "name": "Baza Antifungal",
        "price": 1162.34,
        "buyerFirstName": "Anna",
        "buyerLastName": "Parker"
      }
    ]
  },
  {
    "firstName": "Bonnie",
    "lastName": "Fox",
    "sellingProducts": [
      {
        "name": "Growing Pains",
        "price": 1077.37,
        "buyerFirstName": "Sandra",
        "buyerLastName": "Riley"
      },
      {
        "name": "Smooth texture Orange flavor",
        "price": 976.65,
        "buyerLastName": "Stewart"
      },
      {
        "name": "Laser Block 100",
        "price": 1135.43,
        "buyerFirstName": "Sarah",
        "buyerLastName": "Day"
      },
      {
        "name": "Prednisone",
        "price": 550.72
      }
    ]
  },
  {
    "firstName": "Amanda",
    "lastName": "Frazier",
    "sellingProducts": [
      {
        "name": "Budpak Hemorrhoid Anesthetic",
        "price": 1499.29,
        "buyerFirstName": "Diana",
        "buyerLastName": "Harvey"
      },
      {
        "name": "Pollens - Weeds and Garden Plants, Scotch Broom Cytisus scoparius",
        "price": 135.82
      },
      {
        "name": "Etodolac",
        "price": 1443.13,
        "buyerFirstName": "Anna",
        "buyerLastName": "Clark"
      },
      {
        "name": "Fexofenadine HCl and Pseudoephedrine HCI",
        "price": 73.07
      },
      {
        "name": "ORCHID SECRET PACT",
        "price": 59.53
      },
      {
        "name": "Clarins Paris Skin Illusion - 114 cappuccino",
        "price": 811.42,
        "buyerFirstName": "Marie",
        "buyerLastName": "Williamson"
      }
    ]
  },
  {
    "firstName": "Kathy",
    "lastName": "Gilbert",
    "sellingProducts": [
      {
        "name": "Metaxalone",
        "price": 79.94
      },
      {
        "name": "Labetalol hydrochloride",
        "price": 436.38
      },
      {
        "name": "Peter Island Continous sunscreen kids",
        "price": 471.30
      },
      {
        "name": "Glipizide",
        "price": 621.78
      },
      {
        "name": "LV-FX",
        "price": 820.87,
        "buyerFirstName": "Jacqueline",
        "buyerLastName": "Perez"
      },
      {
        "name": "Fosphenytoin Sodium",
        "price": 1334.06,
        "buyerLastName": "Bennett"
      },
      {
        "name": "IOPE RETIGEN MOISTURE TWIN CAKE NO.21",
        "price": 1257.71,
        "buyerLastName": "Mitchell"
      }
    ]
  },
  {
    "firstName": "Nicole",
    "lastName": "Harris",
    "sellingProducts": [
      {
        "name": "Ampicillin",
        "price": 674.63
      },
      {
        "name": "Oxygen",
        "price": 1242.92,
        "buyerLastName": "Fox"
      },
      {
        "name": "Lamotrigine Extended Release",
        "price": 245.63
      },
      {
        "name": "PREMIER VALUE ALLERGY",
        "price": 1127.61,
        "buyerLastName": "Bennett"
      }
    ]
  },
  {
    "lastName": "Harrison",
    "sellingProducts": [
      {
        "name": "Strattera",
        "price": 658.54
      },
      {
        "name": "CEDAX",
        "price": 342.86
      },
      {
        "name": "Meloxicam",
        "price": 809.18,
        "buyerFirstName": "Joshua",
        "buyerLastName": "Murray"
      },
      {
        "name": "Myristica Argentum Sinus Relief",
        "price": 904.52,
        "buyerLastName": "Thompson"
      },
      {
        "name": "Benazepril Hydrochloride and Hydrochlorothiazide",
        "price": 1187.27,
        "buyerFirstName": "Rachel",
        "buyerLastName": "Johnson"
      },
      {
        "name": "Americaine",
        "price": 1165.75,
        "buyerFirstName": "Fred",
        "buyerLastName": "Allen"
      },
      {
        "name": "VITALUMIERE AQUA",
        "price": 1293.09,
        "buyerFirstName": "Brandon",
        "buyerLastName": "Fuller"
      }
    ]
  },
  {
    "firstName": "Diana",
    "lastName": "Harvey",
    "sellingProducts": [
      {
        "name": "BareMinerals Golden Tan matte",
        "price": 110.93
      },
      {
        "name": "Imipramine Hydrochloride",
        "price": 648.69
      },
      {
        "name": "Perrigo Benzoyl Peroxide",
        "price": 873.24,
        "buyerLastName": "Bennett"
      },
      {
        "name": "AMARANTHUS PALMERI POLLEN",
        "price": 623.16
      },
      {
        "name": "Dawn Ultra Antibacterial Hand",
        "price": 969.86,
        "buyerFirstName": "Thomas",
        "buyerLastName": "Snyder"
      },
      {
        "name": "GOONG SECRET CALMING BATH",
        "price": 742.47,
        "buyerFirstName": "Jeremy",
        "buyerLastName": "Woods"
      },
      {
        "name": "Etoposide",
        "price": 1483.96,
        "buyerFirstName": "Billy",
        "buyerLastName": "Parker"
      },
      {
        "name": "Ranitidine",
        "price": 926.64,
        "buyerLastName": "Schmidt"
      }
    ]
  },
  {
    "firstName": "Benjamin",
    "lastName": "Henry",
    "sellingProducts": [
      {
        "name": "Enalapril Maleate",
        "price": 72.71
      },
      {
        "name": "Warfarin Sodium",
        "price": 1379.79,
        "buyerFirstName": "Christine",
        "buyerLastName": "Gomez"
      }
    ]
  },
  {
    "firstName": "Jean",
    "lastName": "Henry",
    "sellingProducts": [
      {
        "name": "Prostate",
        "price": 716.05,
        "buyerFirstName": "Patricia",
        "buyerLastName": "Fuller"
      },
      {
        "name": "TERSI",
        "price": 554.91
      },
      {
        "name": "ESIKA",
        "price": 879.37,
        "buyerFirstName": "Emily",
        "buyerLastName": "Parker"
      }
    ]
  },
  {
    "firstName": "Paula",
    "lastName": "Hill",
    "sellingProducts": [
      {
        "name": "Glipizide and Metformin Hydrochloride",
        "price": 953.60,
        "buyerFirstName": "Nicole",
        "buyerLastName": "Harris"
      }
    ]
  },
  {
    "firstName": "Brenda",
    "lastName": "Howell",
    "sellingProducts": [
      {
        "name": "Isosorbide Mononitrate",
        "price": 789.91,
        "buyerLastName": "Schmidt"
      },
      {
        "name": "Goats Milk",
        "price": 298.53
      },
      {
        "name": "Irbesartan and Hydrochlorothiazide",
        "price": 308.30
      },
      {
        "name": "Azithromycin",
        "price": 813.87,
        "buyerFirstName": "Sandra",
        "buyerLastName": "Riley"
      }
    ]
  },
  {
    "firstName": "Rachel",
    "lastName": "Johnson",
    "sellingProducts": [
      {
        "name": "pain relief",
        "price": 938.23,
        "buyerFirstName": "Paula",
        "buyerLastName": "Hill"
      },
      {
        "name": "Zonisamide",
        "price": 1305.41,
        "buyerFirstName": "Patricia",
        "buyerLastName": "Fuller"
      },
      {
        "name": "Glyburide",
        "price": 95.10
      },
      {
        "name": "Aspirin",
        "price": 925.45,
        "buyerLastName": "Mitchell"
      },
      {
        "name": "Treatment Set TS336667",
        "price": 1466.47,
        "buyerFirstName": "Marie",
        "buyerLastName": "Williamson"
      },
      {
        "name": "Trihexyphenidyl Hydrochloride",
        "price": 64.88
      },
      {
        "name": "Glycopyrrolate",
        "price": 1471.43,
        "buyerFirstName": "Ann",
        "buyerLastName": "Stevens"
      }
    ]
  },
  {
    "firstName": "Patrick",
    "lastName": "King",
    "sellingProducts": [
      {
        "name": "Parsley",
        "price": 519.06
      },
      {
        "name": "Pleo Lat",
        "price": 720.08,
        "buyerFirstName": "Jonathan",
        "buyerLastName": "Rodriguez"
      },
      {
        "name": "Lorazepam",
        "price": 1134.96,
        "buyerFirstName": "Billy",
        "buyerLastName": "Parker"
      }
    ]
  },
  {
    "firstName": "Betty",
    "lastName": "Lawson",
    "sellingProducts": [
      {
        "name": "Wintergreen Isopropyl Alcohol",
        "price": 1397.57,
        "buyerFirstName": "Fred",
        "buyerLastName": "Allen"
      },
      {
        "name": "NEO-POLY-BAC HYDRO",
        "price": 967.32,
        "buyerLastName": "Schmidt"
      },
      {
        "name": "PRIMAXIN",
        "price": 686.66
      }
    ]
  },
  {
    "firstName": "Nicole",
    "lastName": "Martinez",
    "sellingProducts": [
      {
        "name": "Acid Reducer",
        "price": 1443.51,
        "buyerFirstName": "Jacqueline",
        "buyerLastName": "Perez"
      },
      {
        "name": "Nighttime Sleep Aid",
        "price": 1217.11,
        "buyerFirstName": "Arthur",
        "buyerLastName": "Reynolds"
      }
    ]
  },
  {
    "firstName": "Chris",
    "lastName": "Mitchell",
    "sellingProducts": [
      {
        "name": "XANTHIUM STRUMARIUM VAR CANADENSE POLLEN",
        "price": 1091.38,
        "buyerFirstName": "Marie",
        "buyerLastName": "Williamson"
      },
      {
        "name": "CVS Therapeutic Menthol Pain Reliever",
        "price": 1033.42,
        "buyerLastName": "Thompson"
      },
      {
        "name": "TRAMADOL HYDROCHLORIDE",
        "price": 516.48
      }
    ]
  },
  {
    "lastName": "Moreno",
    "sellingProducts": [
      {
        "name": "ERYTHROMYCIN Base Filmtab",
        "price": 117.84
      },
      {
        "name": "Retin-A MICRO",
        "price": 995.98,
        "buyerFirstName": "Sarah",
        "buyerLastName": "Day"
      },
      {
        "name": "Warfarin Sodium",
        "price": 138.83
      },
      {
        "name": "Propranolol Hydrochloride",
        "price": 546.95
      },
      {
        "name": "CHAMOMILLA",
        "price": 37.97
      },
      {
        "name": "Acnezzol Base",
        "price": 710.60,
        "buyerFirstName": "Diana",
        "buyerLastName": "Harvey"
      }
    ]
  },
  {
    "firstName": "Joshua",
    "lastName": "Murray",
    "sellingProducts": [
      {
        "name": "LBEL Couleur Luxe Rouge Amplifier XP amplifying SPF 15",
        "price": 1069.43,
        "buyerLastName": "Baker"
      },
      {
        "name": "Pleo Ginkgo",
        "price": 613.65
      }
    ]
  },
  {
    "firstName": "Anna",
    "lastName": "Parker",
    "sellingProducts": [
      {
        "name": "EMEND",
        "price": 1365.51,
        "buyerLastName": "Cunningham"
      },
      {
        "name": "Acetic Acid",
        "price": 1060.43,
        "buyerFirstName": "Nicole",
        "buyerLastName": "Harris"
      },
      {
        "name": "Gilotrif",
        "price": 1454.77,
        "buyerFirstName": "Christine",
        "buyerLastName": "Gomez"
      }
    ]
  },
  {
    "firstName": "Billy",
    "lastName": "Parker",
    "sellingProducts": [
      {
        "name": "Agaricus Equisetum Special Order",
        "price": 585.93
      },
      {
        "name": "Metoprolol Tartrate",
        "price": 1405.74,
        "buyerLastName": "Harrison"
      },
      {
        "name": "Allopurinol",
        "price": 518.50
      },
      {
        "name": "PredniSONE",
        "price": 286.43
      },
      {
        "name": "Gehwol med Lipidro",
        "price": 421.24
      }
    ]
  },
  {
    "firstName": "Christina",
    "lastName": "Patterson",
    "sellingProducts": [
      {
        "name": "smart sense nicotine",
        "price": 1444.12,
        "buyerLastName": "Harrison"
      },
      {
        "name": "Extra Strength Pain Reliever PM",
        "price": 542.72
      }
    ]
  },
  {
    "lastName": "Peterson",
    "sellingProducts": [
      {
        "name": "Clearskin",
        "price": 968.59,
        "buyerFirstName": "Arthur",
        "buyerLastName": "Reynolds"
      },
      {
        "name": "Leg Cramp Relief",
        "price": 1345.69,
        "buyerLastName": "Schmidt"
      }
    ]
  },
  {
    "firstName": "Arthur",
    "lastName": "Reynolds",
    "sellingProducts": [
      {
        "name": "Flumazenil",
        "price": 1151.37,
        "buyerFirstName": "Chris",
        "buyerLastName": "Mitchell"
      },
      {
        "name": "Topex",
        "price": 1258.49,
        "buyerLastName": "Stewart"
      },
      {
        "name": "PAMO Kill Natural",
        "price": 1181.06,
        "buyerLastName": "Bennett"
      },
      {
        "name": "EPZICOM",
        "price": 895.65,
        "buyerFirstName": "Jean",
        "buyerLastName": "Henry"
      }
    ]
  },
  {
    "firstName": "Jennifer",
    "lastName": "Riley",
    "sellingProducts": [
      {
        "name": "Metformin Hydrochloride",
        "price": 953.99,
        "buyerFirstName": "Patrick",
        "buyerLastName": "King"
      },
      {
        "name": "MEDICATED DANDRUFF",
        "price": 1351.02,
        "buyerFirstName": "Jacqueline",
        "buyerLastName": "Perez"
      },
      {
        "name": "TYLENOL COLD MULTI-SYMPTOM DAYTIME",
        "price": 1010.81,
        "buyerFirstName": "Anna",
        "buyerLastName": "Clark"
      },
      {
        "name": "Amitriptyline Hydrochloride",
        "price": 1453.96,
        "buyerFirstName": "Emily",
        "buyerLastName": "Parker"
      },
      {
        "name": "CALMING DIAPER RASH",
        "price": 700.92,
        "buyerFirstName": "Kathy",
        "buyerLastName": "Gilbert"
      },
      {
        "name": "Allergena",
        "price": 109.32
      }
    ]
  },
  {
    "firstName": "Sandra",
    "lastName": "Riley",
    "sellingProducts": [
      {
        "name": "Butalbital, Aspirin and Caffeine",
        "price": 1010.98,
        "buyerFirstName": "Ann",
        "buyerLastName": "Stevens"
      },
      {
        "name": "DIPYRIDAMOLE",
        "price": 1150.67,
        "buyerFirstName": "Betty",
        "buyerLastName": "Ward"
      },
      {
        "name": "ENBREL",
        "price": 673.97
      },
      {
        "name": "SNORING HP",
        "price": 53.59
      },
      {
        "name": "Alcohol Free Antiseptic",
        "price": 1486.07,
        "buyerLastName": "Mitchell"
      }
    ]
  },
  {
    "firstName": "Jonathan",
    "lastName": "Rodriguez",
    "sellingProducts": [
      {
        "name": "Alternaria alternata",
        "price": 61.24
      },
      {
        "name": "PCA SKIN ACNE",
        "price": 1356.22,
        "buyerLastName": "Harrison"
      },
      {
        "name": "Etomidate",
        "price": 393.94
      },
      {
        "name": "Triamterene and Hydrochlorothiazide",
        "price": 1416.59,
        "buyerLastName": "Fox"
      },
      {
        "name": "Buprenorphine hydrochloride",
        "price": 391.05
      }
    ]
  },
  {
    "lastName": "Schmidt",
    "sellingProducts": [
      {
        "name": "DIVALPROEX SODIUM",
        "price": 1287.03,
        "buyerFirstName": "Benjamin",
        "buyerLastName": "Henry"
      },
      {
        "name": "Topiramate",
        "price": 578.77
      },
      {
        "name": "ROPINIROLE HYDROCHLORIDE",
        "price": 266.44
      },
      {
        "name": "Allopurinol",
        "price": 336.81
      }
    ]
  },
  {
    "firstName": "Thomas",
    "lastName": "Snyder",
    "sellingProducts": [
      {
        "name": "Fair Foundation SPF 15",
        "price": 1394.24,
        "buyerLastName": "Mitchell"
      },
      {
        "name": "allergy eye",
        "price": 426.91
      },
      {
        "name": "Levothyroxine Sodium",
        "price": 885.86,
        "buyerFirstName": "Joshua",
        "buyerLastName": "Murray"
      }
    ]
  },
  {
    "firstName": "Ann",
    "lastName": "Stevens",
    "sellingProducts": [
      {
        "name": "Archangelica Eucalyptus",
        "price": 1334.91,
        "buyerLastName": "Lawson"
      },
      {
        "name": "ESIKA 3-IN-1 PRO MAKE UP FOUNDATION SPF 20 BASE DE MAQUILLAJE PARA ROSTRO 3-EN-1 PRO FPS 20",
        "price": 1097.60,
        "buyerFirstName": "Wanda",
        "buyerLastName": "Harris"
      }
    ]
  },
  {
    "lastName": "Stewart",
    "sellingProducts": [
      {
        "name": "Foaming Hand Sanitizer",
        "price": 624.72
      },
      {
        "name": "Spironolactone",
        "price": 933.69,
        "buyerFirstName": "Bonnie",
        "buyerLastName": "Fox"
      },
      {
        "name": "Carbon Dioxide Oxygen Mixture",
        "price": 95.49
      },
      {
        "name": "Aspen",
        "price": 1046.46,
        "buyerFirstName": "Christine",
        "buyerLastName": "Gomez"
      }
    ]
  },
  {
    "firstName": "Eugene",
    "lastName": "Stewart",
    "sellingProducts": [
      {
        "name": "Fluoxetine",
        "price": 385.37
      },
      {
        "name": "smart sense nighttime cold and flu relief",
        "price": 1101.77,
        "buyerLastName": "Schmidt"
      },
      {
        "name": "Head and Shoulders Conditioner",
        "price": 1099.59,
        "buyerFirstName": "Gary",
        "buyerLastName": "Stevens"
      },
      {
        "name": "Warfarin Sodium",
        "price": 770.05,
        "buyerFirstName": "Gary",
        "buyerLastName": "Stevens"
      },
      {
        "name": "Naproxen",
        "price": 807.22,
        "buyerFirstName": "Christine",
        "buyerLastName": "Gomez"
      }
    ]
  },
  {
    "lastName": "Thompson",
    "sellingProducts": [
      {
        "name": "Aquafresh",
        "price": 849.93,
        "buyerFirstName": "Jonathan",
        "buyerLastName": "Rodriguez"
      },
      {
        "name": "Megestrol Acetate",
        "price": 976.15,
        "buyerFirstName": "Amanda",
        "buyerLastName": "Frazier"
      },
      {
        "name": "Pollens - Trees, Birch Mix",
        "price": 1153.54,
        "buyerFirstName": "Fred",
        "buyerLastName": "Barnes"
      },
      {
        "name": "Hydralazine Hydrochloride",
        "price": 1309.72,
        "buyerFirstName": "Gary",
        "buyerLastName": "Stevens"
      },
      {
        "name": "RESCRIPTOR",
        "price": 850.52,
        "buyerLastName": "Mitchell"
      },
      {
        "name": "Moore Medical Sinus Pain and Pressure Relief",
        "price": 855.39,
        "buyerFirstName": "Joshua",
        "buyerLastName": "Murray"
      },
      {
        "name": "Ketorolac Tromethamine",
        "price": 608.18
      }
    ]
  },
  {
    "firstName": "Betty",
    "lastName": "Ward",
    "sellingProducts": [
      {
        "name": "Cold and Cough",
        "price": 218.14
      },
      {
        "name": "CARBIDOPA AND LEVODOPA",
        "price": 441.64
      },
      {
        "name": "Nevirapine",
        "price": 1374.72,
        "buyerFirstName": "Jonathan",
        "buyerLastName": "Rodriguez"
      }
    ]
  },
  {
    "firstName": "Marie",
    "lastName": "Williamson",
    "sellingProducts": [
      {
        "name": "Amlodipine Besylate",
        "price": 122.57
      },
      {
        "name": "Prednisone",
        "price": 1285.99,
        "buyerFirstName": "Thomas",
        "buyerLastName": "Snyder"
      },
      {
        "name": "Aspergillus repens",
        "price": 1231.42,
        "buyerFirstName": "Fred",
        "buyerLastName": "Allen"
      },
      {
        "name": "Topical 60 Sec Sodium Fluoride",
        "price": 1228.84,
        "buyerFirstName": "Nicole",
        "buyerLastName": "Martinez"
      },
      {
        "name": "Pioglitazone",
        "price": 306.56
      },
      {
        "name": "equaline",
        "price": 520.45
      }
    ]
  },
  {
    "firstName": "Jeremy",
    "lastName": "Woods",
    "sellingProducts": [
      {
        "name": "Ringers",
        "price": 1054.37,
        "buyerFirstName": "Marie",
        "buyerLastName": "Williamson"
      },
      {
        "name": "AVANDAMET",
        "price": 632.08
      }
    ]
  }
]